bluzelle/__init__.py
bluzelle/bluzelle.py
bluzelle/mnemonic_utils.py
bluzelle-0.1.1.dist-info/METADATA
bluzelle-0.1.1.dist-info/WHEEL
bluzelle-0.1.1.dist-info/top_level.txt
bluzelle-0.1.1.dist-info/zip-safe
bluzelle-0.1.1.dist-info/RECORD
