Metadata-Version: 2.1
Name: bluzelle
Version: 0.1.1
Summary: Python library for the Bluzelle Service.
Home-page: https://github.com/vbstreetz/blzpy
Author: vbstreetz
Author-email: vbstreetz@gmail.com
License: MIT License
Keywords: bluzelle tendermint cosmos
Platform: UNKNOWN
Classifier: Topic :: Utilities
Requires-Dist: requests
Requires-Dist: base58
Requires-Dist: ecdsa
Requires-Dist: bech32
